jsoncsv/__init__.py
jsoncsv/dumptool.py
jsoncsv/jsontool.py
jsoncsv/main.py
jsoncsv/utils.py
jsoncsv-2.2.2.dist-info/METADATA
jsoncsv-2.2.2.dist-info/RECORD
jsoncsv-2.2.2.dist-info/WHEEL
jsoncsv-2.2.2.dist-info/entry_points.txt
jsoncsv-2.2.2.dist-info/top_level.txt
