Metadata-Version: 2.1
Name: jsoncsv
Version: 2.2.2
Summary: A command tool easily convert json file to csv or xlsx.
Home-page: https://github.com/alingse/jsoncsv
Author: alingse
Author-email: alingse@foxmail.com
License: Apache 2.0
Keywords: jsontocsv,json2csv,jsoncsv,command,convert,json,csv,xls
Platform: UNKNOWN
Classifier: Operating System :: OS Independent
Classifier: Programming Language :: Python
Classifier: Programming Language :: Python :: 2
Classifier: Programming Language :: Python :: 2.7
Classifier: Programming Language :: Python :: 3
Classifier: Programming Language :: Python :: 3.5
Classifier: Programming Language :: Python :: 3.6
Classifier: Programming Language :: Python :: 3.7
Requires-Dist: unicodecsv
Requires-Dist: xlwt
Requires-Dist: click
